<?xml version="1.0"?>
<opencv_storage>
<stage4>
  <maxWeakCount>8</maxWeakCount>
  <stageThreshold>-2.4424245357513428e+00</stageThreshold>
  <weakClassifiers>
    <_>
      <internalNodes>
        0 -1 647 -1 -1 -268435457 -1 -1 -4105 -1 -1</internalNodes>
      <leafValues>
        -9.1292673349380493e-01 5.0632911920547485e-01</leafValues></_>
    <_>
      <internalNodes>
        0 -1 8089 -536876289 -34365764 1599029467 -113248558 -1619789057
        -1148551970 226224346 -10486053</internalNodes>
      <leafValues>
        -6.8123161792755127e-01 5.2073817700147629e-02</leafValues></_>
    <_>
      <internalNodes>
        0 -1 7421 -1032329978 1375649738 2097052639 557872887 -537050238
        -1166606467 -742437170 -1305219085</internalNodes>
      <leafValues>
        -4.8898011445999146e-01 2.1551543474197388e-01</leafValues></_>
    <_>
      <internalNodes>
        0 -1 3982 -1348409436 663158400 -1091066256 -1770047 25146855
        -1879195667 -1212713034 669603285</internalNodes>
      <leafValues>
        -5.6539928913116455e-01 2.1873022615909576e-01</leafValues></_>
    <_>
      <internalNodes>
        0 -1 7944 -1116774650 1329487407 -1627408670 615448310
        -671911931 1180041039 -168139562 -201655433</internalNodes>
      <leafValues>
        -4.6475923061370850e-01 2.8068512678146362e-01</leafValues></_>
    <_>
      <internalNodes>
        0 -1 3394 -1389226688 -1568559264 -201894928 -1364411103
        -2062876681 1190095855 364897121 216794608</internalNodes>
      <leafValues>
        -7.3209202289581299e-01 2.2000962495803833e-01</leafValues></_>
    <_>
      <internalNodes>
        0 -1 8034 140380188 289038319 922676991 1882910717 1962831434
        -595595393 -806126339 -1431286252</internalNodes>
      <leafValues>
        -5.2889049053192139e-01 2.3704017698764801e-01</leafValues></_>
    <_>
      <internalNodes>
        0 -1 7617 -319883360 -1076703445 -252212016 1168949108
        2099214217 87482271 1165952748 83832151</internalNodes>
      <leafValues>
        -5.7030695676803589e-01 2.2284899652004242e-01</leafValues></_></weakClassifiers></stage4>
</opencv_storage>
